.gitignore
LICENSE
README.rst
manage.py
setup.py
django_promoter/__init__.py
django_promoter.egg-info/PKG-INFO
django_promoter.egg-info/SOURCES.txt
django_promoter.egg-info/dependency_links.txt
django_promoter.egg-info/top_level.txt
django_promoter/management/__init__.py
django_promoter/management/commands/__init__.py
django_promoter/management/commands/demote.py
django_promoter/management/commands/promote.py