Metadata-Version: 1.1
Name: django-promoter
Version: 1.0.1
Summary: Django commands used to promote or demote users
Home-page: https://github.com/numberly/django-promoter
Author: Theo Massard
Author-email: theo.massard@1000mercis.com
License: MIT
Keywords: django auth admin cli python3.5
Platform: UNKNOWN
Classifier: Development Status :: 5 - Production/Stable
Classifier: Environment :: Console
Classifier: Framework :: Django
Classifier: Intended Audience :: Developers
Classifier: Intended Audience :: System Administrators
Classifier: License :: OSI Approved :: MIT License
Classifier: Programming Language :: Python :: 3
Classifier: Programming Language :: Python :: 3.5
